hyprctl/__init__.py
hyprctl/parse.py
hyprctl/utils.py
hyprctl/ctl/__init__.py
hyprctl/ctl/base.py
hyprctl/ctl/commands.py
hyprctl/ctl/info.py
hyprctl/router/__init__.py
hyprctl/router/dispatcher.py
hyprctl/router/router.py
hyprctl/types/__init__.py
hyprctl/types/color.py
hyprctl/types/ctl.py
hyprctl/types/enums.py
hyprctl/types/events.py
hyprctl-1.0.2.dist-info/METADATA
hyprctl-1.0.2.dist-info/WHEEL
hyprctl-1.0.2.dist-info/top_level.txt
hyprctl-1.0.2.dist-info/RECORD
